MANIFEST.in
setup.cfg
setup.py
docs/Makefile
docs/source/conf.py
docs/source/index.rst
docs/source/usingmorpfw.rst
morpfw/__init__.py
morpfw/app.py
morpfw/directive.py
morpfw/exc.py
morpfw/main.py
morpfw/permission_rule.py
morpfw/sql.py
morpfw/util.py
morpfw.egg-info/PKG-INFO
morpfw.egg-info/SOURCES.txt
morpfw.egg-info/dependency_links.txt
morpfw.egg-info/entry_points.txt
morpfw.egg-info/not-zip-safe
morpfw.egg-info/requires.txt
morpfw.egg-info/top_level.txt
morpfw/authmanager/__init__.py
morpfw/authmanager/action.py
morpfw/authmanager/app.py
morpfw/authmanager/authpolicy.py
morpfw/authmanager/exc.py
morpfw/authmanager/path.py
morpfw/authmanager/permission.py
morpfw/authmanager/utils.py
morpfw/authmanager/validator.py
morpfw/authmanager/dbmodel/__init__.py
morpfw/authmanager/dbmodel/apikey.py
morpfw/authmanager/dbmodel/group.py
morpfw/authmanager/dbmodel/user.py
morpfw/authmanager/model/__init__.py
morpfw/authmanager/model/apikey.py
morpfw/authmanager/model/base.py
morpfw/authmanager/model/group.py
morpfw/authmanager/model/user.py
morpfw/authmanager/storage/__init__.py
morpfw/authmanager/storage/interfaces.py
morpfw/authmanager/storage/memorystorage.py
morpfw/authmanager/storage/sqlstorage.py
morpfw/authmanager/view/__init__.py
morpfw/authmanager/view/apikey.py
morpfw/authmanager/view/common.py
morpfw/authmanager/view/group.py
morpfw/authmanager/view/user.py
morpfw/avro/__init__.py
morpfw/avro/jsl_to_avro.py
morpfw/jslcrud/__init__.py
morpfw/jslcrud/app.py
morpfw/jslcrud/component.py
morpfw/jslcrud/const.py
morpfw/jslcrud/errors.py
morpfw/jslcrud/log.py
morpfw/jslcrud/model.py
morpfw/jslcrud/permission.py
morpfw/jslcrud/pubsub.py
morpfw/jslcrud/security.py
morpfw/jslcrud/signals.py
morpfw/jslcrud/subscribers.py
morpfw/jslcrud/types.py
morpfw/jslcrud/util.py
morpfw/jslcrud/validator.py
morpfw/jslcrud/view.py
morpfw/jslcrud/provider/__init__.py
morpfw/jslcrud/provider/base.py
morpfw/jslcrud/provider/dictprovider.py
morpfw/jslcrud/provider/esdictprovider.py
morpfw/jslcrud/provider/samodelprovider.py
morpfw/jslcrud/storage/__init__.py
morpfw/jslcrud/storage/base.py
morpfw/jslcrud/storage/elasticsearchstorage.py
morpfw/jslcrud/storage/memorystorage.py
