Metadata-Version: 2.1
Name: morpfw
Version: 0.1.3
Summary: Web framework based on morepath
Home-page: http://github.com/morpframework/morpfw
Author: Izhar Firdaus
Author-email: izhar@abyres.net
License: MIT
Platform: UNKNOWN
Provides-Extra: test
